{
  "utrecht": {
    "flo-decision": {
      "explanation": {
        "margin-inline-start": {
          "$extensions": {
            "nl.nldesignsystem.css.property": {
              "syntax": "<length>",
              "inherits": true
            },
            "nl.nldesignsystem.figma.supports-token": true
          },
          "type": "spacing"
        },
        "margin-block-start": {
          "$extensions": {
            "nl.nldesignsystem.css.property": {
              "syntax": "<length>",
              "inherits": true
            },
            "nl.nldesignsystem.figma.supports-token": true
          },
          "type": "spacing"
        },
        "button": {
          "border-color": {
            "$extensions": {
              "nl.nldesignsystem.css.property": {
                "syntax": "<color>",
                "inherits": true
              },
              "nl.nldesignsystem.figma.supports-token": true
            },
            "type": "color"
          },
          "background-color": {
            "$extensions": {
              "nl.nldesignsystem.css.property": {
                "syntax": "<color>",
                "inherits": true
              },
              "nl.nldesignsystem.figma.supports-token": true
            },
            "type": "color"
          },
          "close": {
            "margin-block-end": {
              "$extensions": {
                "nl.nldesignsystem.css.property": {
                  "syntax": "<length>",
                  "inherits": true
                },
                "nl.nldesignsystem.figma.supports-token": true
              },
              "type": "spacing"
            }
          }
        },
        "container": {
          "background-color": {
            "$extensions": {
              "nl.nldesignsystem.css.property": {
                "syntax": "<color>",
                "inherits": true
              },
              "nl.nldesignsystem.figma.supports-token": true
            },
            "type": "color"
          },
          "margin-block-start": {
            "$extensions": {
              "nl.nldesignsystem.css.property": {
                "syntax": "<length>",
                "inherits": true
              },
              "nl.nldesignsystem.figma.supports-token": true
            },
            "type": "spacing"
          }
        }
      },
      "label": {
        "checkbox": {
          "column-gap": {
            "$extensions": {
              "nl.nldesignsystem.css.property": {
                "syntax": "<length>",
                "inherits": true
              },
              "nl.nldesignsystem.figma.supports-token": true
            },
            "type": "spacing"
          },
          "margin-block-start": {
            "$extensions": {
              "nl.nldesignsystem.css.property": {
                "syntax": "<length>",
                "inherits": true
              },
              "nl.nldesignsystem.figma.supports-token": true
            },
            "type": "spacing"
          }
        }
      },
      "form": {
        "padding-block": {
          "$extensions": {
            "nl.nldesignsystem.css.property": {
              "syntax": "<length>",
              "inherits": true
            },
            "nl.nldesignsystem.figma.supports-token": true
          },
          "type": "spacing"
        },
        "padding-inline": {
          "$extensions": {
            "nl.nldesignsystem.css.property": {
              "syntax": "<length>",
              "inherits": true
            },
            "nl.nldesignsystem.figma.supports-token": true
          },
          "type": "spacing"
        },
        "background-color": {
          "$extensions": {
            "nl.nldesignsystem.css.property": {
              "syntax": "<color>",
              "inherits": true
            },
            "nl.nldesignsystem.figma.supports-token": true
          },
          "type": "color"
        },
        "margin-block-start": {
          "$extensions": {
            "nl.nldesignsystem.css.property": {
              "syntax": "<length>",
              "inherits": true
            },
            "nl.nldesignsystem.figma.supports-token": true
          },
          "type": "spacing"
        },
        "margin-block-end": {
          "$extensions": {
            "nl.nldesignsystem.css.property": {
              "syntax": "<length>",
              "inherits": true
            },
            "nl.nldesignsystem.figma.supports-token": true
          },
          "type": "spacing"
        },
        "button": {
          "disabled": {
            "color": {
              "$extensions": {
                "nl.nldesignsystem.css.property": {
                  "syntax": "<color>",
                  "inherits": true
                },
                "nl.nldesignsystem.figma.supports-token": true
              },
              "type": "color"
            }
          }
        },
        "nav": {
          "padding-block": {
            "$extensions": {
              "nl.nldesignsystem.css.property": {
                "syntax": "<length>",
                "inherits": true
              },
              "nl.nldesignsystem.figma.supports-token": true
            },
            "type": "spacing"
          },
          "background-color": {
            "$extensions": {
              "nl.nldesignsystem.css.property": {
                "syntax": "<color>",
                "inherits": true
              },
              "nl.nldesignsystem.figma.supports-token": true
            },
            "type": "color"
          }
        }
      },
      "question": {
        "description": {
          "column-gap": {
            "$extensions": {
              "nl.nldesignsystem.css.property": {
                "syntax": "<length>",
                "inherits": true
              },
              "nl.nldesignsystem.figma.supports-token": true
            },
            "type": "spacing"
          }
        },
        "answers": {
          "row-gap": {
            "$extensions": {
              "nl.nldesignsystem.css.property": {
                "syntax": "<length>",
                "inherits": true
              },
              "nl.nldesignsystem.figma.supports-token": true
            },
            "type": "spacing"
          },
          "option": {
            "column-gap": {
              "$extensions": {
                "nl.nldesignsystem.css.property": {
                  "syntax": "<length>",
                  "inherits": true
                },
                "nl.nldesignsystem.figma.supports-token": true
              },
              "type": "spacing"
            }
          }
        },
        "section": {
          "padding-block-end": {
            "$extensions": {
              "nl.nldesignsystem.css.property": {
                "syntax": "<length>",
                "inherits": true
              },
              "nl.nldesignsystem.figma.supports-token": true
            },
            "type": "spacing"
          },
          "padding-block-start": {
            "$extensions": {
              "nl.nldesignsystem.css.property": {
                "syntax": "<length>",
                "inherits": true
              },
              "nl.nldesignsystem.figma.supports-token": true
            },
            "type": "spacing"
          },
          "background-color": {
            "$extensions": {
              "nl.nldesignsystem.css.property": {
                "syntax": "<color>",
                "inherits": true
              },
              "nl.nldesignsystem.figma.supports-token": true
            },
            "type": "color"
          },
          "border-block-color": {
            "$extensions": {
              "nl.nldesignsystem.css.property": {
                "syntax": "<color>",
                "inherits": true
              },
              "nl.nldesignsystem.figma.supports-token": true
            },
            "type": "color"
          },
          "border-block-width": {
            "$extensions": {
              "nl.nldesignsystem.css.property": {
                "syntax": "<length>",
                "inherits": true
              },
              "nl.nldesignsystem.figma.supports-token": true
            },
            "type": "borderWidth"
          }
        }
      },
      "outcomes-container": {
        "background-color": {
          "$extensions": {
            "nl.nldesignsystem.css.property": {
              "syntax": "<color>",
              "inherits": true
            },
            "nl.nldesignsystem.figma.supports-token": true
          },
          "type": "color"
        },
        "margin-block-start": {
          "$extensions": {
            "nl.nldesignsystem.css.property": {
              "syntax": "<length>",
              "inherits": true
            },
            "nl.nldesignsystem.figma.supports-token": true
          },
          "type": "spacing"
        },
        "padding-inline": {
          "$extensions": {
            "nl.nldesignsystem.css.property": {
              "syntax": "<length>",
              "inherits": true
            },
            "nl.nldesignsystem.figma.supports-token": true
          },
          "type": "spacing"
        },
        "padding-block": {
          "$extensions": {
            "nl.nldesignsystem.css.property": {
              "syntax": "<length>",
              "inherits": true
            },
            "nl.nldesignsystem.figma.supports-token": true
          },
          "type": "spacing"
        }
      }
    }
  }
}
