{
  "utrecht": {
    "focus": {
      "background-color": {
        "css": {
          "syntax": "<color>",
          "inherits": true
        }
      },
      "border-color": {
        "css": {
          "syntax": "<color>",
          "inherits": true
        }
      },
      "border-style": {
        "css": {
          "syntax": "dotted | none | solid",
          "inherits": true
        }
      },
      "box-shadow-color": {
        "css": {
          "syntax": "<color>",
          "inherits": true
        }
      },
      "box-shadow-spread-radius": {
        "css": {
          "syntax": "<length>",
          "inherits": true
        }
      },
      "color": {
        "css": {
          "syntax": "<color>",
          "inherits": true
        }
      },
      "outline-color": {
        "css": {
          "syntax": "<color>",
          "inherits": true
        }
      },
      "outline-offset": {
        "css": {
          "syntax": "<length>",
          "inherits": true
        }
      },
      "outline-style": {
        "css": {
          "syntax": "dotted | none | solid",
          "inherits": true
        }
      },
      "outline-width": {
        "css": {
          "syntax": "<length>",
          "inherits": true
        }
      }
    }
  }
}
