{
  "utrecht": {
    "card": {
      "background-color": {
        "$extensions": {
          "nl.nldesignsystem.css-property-syntax": "<color>",
          "nl.nldesignsystem.figma-implementation": false
        },
        "$type": "color"
      },
      "color": {
        "$extensions": {
          "nl.nldesignsystem.css-property-syntax": "<color>",
          "nl.nldesignsystem.figma-implementation": false
        },
        "$type": "color"
      },
      "max-inline-size": {
        "$extensions": {
          "nl.nldesignsystem.css-property-syntax": "<length>",
          "nl.nldesignsystem.figma-implementation": false
        },
        "$type": "dimension"
      },
      "border-radius": {
        "$extensions": {
          "nl.nldesignsystem.css-property-syntax": "<length>",
          "nl.nldesignsystem.figma-implementation": false
        },
        "$type": "dimension"
      },
      "box-shadow": {
        "$extensions": {
          "nl.nldesignsystem.css-property-syntax": "<shadow>",
          "nl.nldesignsystem.figma-implementation": false
        },
        "$type": "shadow"
      },
      "inline-size": {
        "$extensions": {
          "nl.nldesignsystem.css-property-syntax": "<length>",
          "nl.nldesignsystem.figma-implementation": false
        },
        "$type": "dimension"
      },
      "row-gap": {
        "$extensions": {
          "nl.nldesignsystem.css-property-syntax": "<length>",
          "nl.nldesignsystem.figma-implementation": false
        },
        "$type": "dimension"
      },
      "heading": {
        "color": {
          "$extensions": {
            "nl.nldesignsystem.css-property-syntax": "<color>",
            "nl.nldesignsystem.figma-implementation": false
          },
          "$type": "color"
        },
        "padding-inline-start": {
          "$extensions": {
            "nl.nldesignsystem.css-property-syntax": "<length>",
            "nl.nldesignsystem.figma-implementation": false
          },
          "$type": "dimension"
        },
        "padding-inline-end": {
          "$extensions": {
            "nl.nldesignsystem.css-property-syntax": "<length>",
            "nl.nldesignsystem.figma-implementation": false
          },
          "$type": "dimension"
        }
      },
      "link": {
        "hover": {
          "text-decoration-thickness": {
            "$extensions": {
              "nl.nldesignsystem.css-property-syntax": "<length>",
              "nl.nldesignsystem.figma-implementation": false
            },
            "$type": "dimension"
          }
        }
      },
      "content": {
        "row-gap": {
          "$extensions": {
            "nl.nldesignsystem.css-property-syntax": "<length>",
            "nl.nldesignsystem.figma-implementation": false
          },
          "$type": "dimension"
        },
        "padding-block-start": {
          "$extensions": {
            "nl.nldesignsystem.css-property-syntax": "<length>",
            "nl.nldesignsystem.figma-implementation": false
          },
          "$type": "dimension"
        },
        "padding-block-end": {
          "$extensions": {
            "nl.nldesignsystem.css-property-syntax": "<length>",
            "nl.nldesignsystem.figma-implementation": false
          },
          "$type": "dimension"
        }
      },
      "body": {
        "padding-inline-start": {
          "$extensions": {
            "nl.nldesignsystem.css-property-syntax": "<length>",
            "nl.nldesignsystem.figma-implementation": false
          },
          "$type": "dimension"
        },
        "padding-inline-end": {
          "$extensions": {
            "nl.nldesignsystem.css-property-syntax": "<length>",
            "nl.nldesignsystem.figma-implementation": false
          },
          "$type": "dimension"
        }
      }
    }
  }
}
