{
  "utrecht": {
    "heading-4": {
      "color": {},
      "font-family": { "value": "{utrecht.typography.sans-serif.font-family}" },
      "font-size": { "value": "{utrecht.typography.scale.lg.font-size}" },
      "font-weight": { "value": "{utrecht.typography.weight-scale.normal.font-weight}" },
      "line-height": { "value": "{utrecht.typography.line-height.md}" },
      "margin-block-end": { "value": "0.3rem" },
      "margin-block-start": { "value": "1.2rem" },
      "letter-spacing": { "value": "{utrecht.typography.letter-spacing.normal}" },
      "text-transform": {}
    }
  }
}
